luminarycloud_jupyter/__init__.py
luminarycloud_jupyter/_version.py
luminarycloud_jupyter/ensemble_widget.py
luminarycloud_jupyter/interactive_lcvis_widget.py
luminarycloud_jupyter/lcvis_widget.py
luminarycloud_jupyter/vis_enums.py
luminarycloud_jupyter/static/ensemble_widget.js
luminarycloud_jupyter/static/lcvis.js
luminarycloud_jupyter/static/v0.10.1.8c96e7a364e1370bda76.wasm
luminarycloud_jupyter-0.1.20.dist-info/METADATA
luminarycloud_jupyter-0.1.20.dist-info/WHEEL
luminarycloud_jupyter-0.1.20.dist-info/RECORD
