Metadata-Version: 2.4
Name: luminarycloud_jupyter
Version: 0.1.20
Summary: Luminary Cloud SDK Interactive Jupyter Widgets
Project-URL: Homepage, https://www.luminarycloud.com/
Project-URL: Documentation, https://app.luminarycloud.com/docs/api/
Author-email: "Luminary Cloud Inc." <support@luminarycloud.com>
Keywords: Jupyter,Luminary Cloud,SDK
Requires-Python: >=3.10
Requires-Dist: anywidget==0.9.0
Requires-Dist: ipython-genutils==0.2.0
Requires-Dist: ipywidgets==7.6.0
Requires-Dist: jupyterlab<5,>=4.2.4
Requires-Dist: luminarycloud~=0.22.2
Requires-Dist: requests~=2.28
